funnygpt/__init__.py
funnygpt/functions.py
funnygpt-1.0.9.dist-info/LICENSE
funnygpt-1.0.9.dist-info/METADATA
funnygpt-1.0.9.dist-info/WHEEL
funnygpt-1.0.9.dist-info/top_level.txt
funnygpt-1.0.9.dist-info/RECORD
