Metadata-Version: 2.1
Name: funnygpt
Version: 1.0.9
Summary: A package for project 3 for stuytowners
Author-email: Luke Bernstein <lnb337@nyu.edu>, Angela Tao <xt2016@nyu.edu>, Charles Hu <cch9399@nyu.edu>, James Luo <jl11335@nyu.edu>
Project-URL: Homepage, https://github.com/software-students-fall2023/3-python-package-exercise-stuytowners/tree/main
Classifier: Programming Language :: Python :: 3
Classifier: License :: OSI Approved :: MIT License
Classifier: Operating System :: OS Independent
Requires-Python: >=3.7
License-File: LICENSE
Requires-Dist: openai >=1.1.1
